{"cameraMode":{"drawMode":0,"name":"Shaded","section":"Shading Mode"},"sceneLighting":true,"audioPlay":false,"sceneViewState":{"showFog":true,"showMaterialUpdate":false,"showSkybox":true,"showFlares":true,"showImageEffects":true,"showParticleSystems":true},"in2DMode":false,"pivot":{"x":31.410396575927736,"y":34.72907638549805,"z":10.720478057861329},"rotation":{"x":0.21331816911697389,"y":-0.7730569839477539,"z":0.3316483497619629,"w":0.49699440598487856},"size":3.2105658054351808,"orthographic":false}